hack4u/__init__.py
hack4u/courses.py
hack4u/utils.py
Hack4u_Allen-0.5.13.dist-info/METADATA
Hack4u_Allen-0.5.13.dist-info/WHEEL
Hack4u_Allen-0.5.13.dist-info/top_level.txt
Hack4u_Allen-0.5.13.dist-info/RECORD
