Metadata-Version: 2.1
Name: Hack4u-Allen
Version: 0.5.13
Summary: Una biblioteca para consultar tus cursos de hack4u
Home-page: https://hack4u.io
Author: Marcelo Vásquez
